mochic_4/__init__.py
mochic_4/config.py
mochic_4/hpc.py
mochic_4/py.typed
mochic_4/scripts/main.py
mochic_4-0.1.1.dist-info/LICENSE
mochic_4-0.1.1.dist-info/METADATA
mochic_4-0.1.1.dist-info/WHEEL
mochic_4-0.1.1.dist-info/top_level.txt
mochic_4-0.1.1.dist-info/RECORD
