Metadata-Version: 2.1
Name: mochic-4
Version: 0.1.1
Author-email: Chris Mochizuki <chrism@alleninstitute.org>
License: MIT
Project-URL: Repository, https://github.com/AllenInstitute/mochic-4
Project-URL: Issues, https://github.com/AllenInstitute/mochic-4/issues
Classifier: Development Status :: 3 - Alpha
Classifier: Programming Language :: Python :: 3
Classifier: Programming Language :: Python :: 3.9
Classifier: Programming Language :: Python :: 3.10
Classifier: Programming Language :: Python :: 3.11
Classifier: License :: OSI Approved :: MIT License
Classifier: Operating System :: Microsoft :: Windows
Classifier: Operating System :: POSIX :: Linux
Requires-Python: >=3.9
License-File: LICENSE
Requires-Dist: python-dotenv >=1.0.1
Requires-Dist: fabric >=3.2.2
Requires-Dist: pydantic >=2.7.1
Requires-Dist: click >=8.1.7
